proportional_navigation/__init__.py
proportional_navigation/exceptions.py
proportional_navigation/models.py
proportional_navigation/proportional_navigation.py
proportional_navigation-1.1.2.dist-info/LICENSE
proportional_navigation-1.1.2.dist-info/METADATA
proportional_navigation-1.1.2.dist-info/WHEEL
proportional_navigation-1.1.2.dist-info/top_level.txt
proportional_navigation-1.1.2.dist-info/RECORD
