Metadata-Version: 2.1
Name: proportional-navigation
Version: 1.1.2
Summary: A package to do proportional navigation
Home-page: https://github.com/iwishiwasaneagle/proportional_navigation
Author: Jan-Hendrik Ewers
Author-email: jh.ewers@gmail.com
License: UNKNOWN
Platform: UNKNOWN
Classifier: Programming Language :: Python :: 3
Classifier: License :: OSI Approved :: MIT License
Classifier: Operating System :: OS Independent
Requires-Python: >=3.6
